README.md
setup.py
sndtrck/__init__.py
sndtrck/analysis.py
sndtrck/analyzer_python.py
sndtrck/backend_loris.py
sndtrck/backend_pysdif.py
sndtrck/background.py
sndtrck/config.py
sndtrck/const.py
sndtrck/errors.py
sndtrck/fx.py
sndtrck/interact.py
sndtrck/io.py
sndtrck/multisine-player.csd
sndtrck/pack.py
sndtrck/partial.py
sndtrck/plot.py
sndtrck/plotpyqtgraph.py
sndtrck/reduction.py
sndtrck/sinesynth.py
sndtrck/spectralsurface.py
sndtrck/spectrum-player.csd
sndtrck/spectrum.py
sndtrck/synthesis.py
sndtrck/typehints.py
sndtrck/util.py
sndtrck/version.py
sndtrck.egg-info/PKG-INFO
sndtrck.egg-info/SOURCES.txt
sndtrck.egg-info/dependency_links.txt
sndtrck.egg-info/pbr.json
sndtrck.egg-info/requires.txt
sndtrck.egg-info/top_level.txt