Metadata-Version: 2.1
Name: sndtrck
Version: 0.5.0
Summary: Sound manipulation and representation via partial-tracking
Home-page: UNKNOWN
Author: Eduardo Moguillansky
License: UNKNOWN
Platform: UNKNOWN
